DaemonLite.py
README.rst
setup.py
DaemonLite.egg-info/PKG-INFO
DaemonLite.egg-info/SOURCES.txt
DaemonLite.egg-info/dependency_links.txt
DaemonLite.egg-info/top_level.txt
tests/__init__.py