Metadata-Version: 1.1
Name: DaemonLite
Version: 0.0.2
Summary: This is a Python class that will daemonize your Python script so it can continue running in the background
Home-page: https://github.com/laodifang/DaemonLite.git
Author: Ren Peng
Author-email: ithink.ren@gmail.com
License: MIT
Keywords: Python Daemon
Platform: UNKNOWN
Classifier: Development Status :: 5 - Production/Stable
Classifier: Intended Audience :: Developers
Classifier: License :: OSI Approved :: MIT License
Classifier: Programming Language :: Python :: 3.4
Classifier: Programming Language :: Python :: 3 :: Only
